sitec/__init__.py
sitec/__main__.py
sitec/__version__.py
sitec/classes.py
sitec/constants.py
sitec/enums.py
sitec/exceptions.py
sitec/functions.py
sitec/sitec.pth
sitec/typings.py
sitec/variables.py
sitec/cli/__init__.py
sitec/cli/app.py
sitec/cli/pth.py
sitec/cli/requirements.py
sitec/cli/venv.py
sitec-0.1.3.dist-info/METADATA
sitec-0.1.3.dist-info/WHEEL
sitec-0.1.3.dist-info/entry_points.txt
sitec-0.1.3.dist-info/top_level.txt
sitec-0.1.3.dist-info/RECORD
