Metadata-Version: 2.1
Name: sitec
Version: 0.1.3
Summary: site customize
License: MIT
Requires-Python: >=3.10
Requires-Dist: beautifulsoup4 <5,>=4.12.2
Requires-Dist: requests <3,>=2.31.0
Requires-Dist: rich <14,>=13.5
Requires-Dist: python-decouple <4,>=3.8
Requires-Dist: semver <4,>=3.0.1
Requires-Dist: toml <1,>=0.10.2
Requires-Dist: typer[all] <1,>=0.9
Provides-Extra: dev
Requires-Dist: black ; extra == 'dev'
Requires-Dist: icecream ; extra == 'dev'
Requires-Dist: ipython ; extra == 'dev'
Requires-Dist: ipython-suggestions ; extra == 'dev'
Requires-Dist: restmagic ; extra == 'dev'
Requires-Dist: mypy ; extra == 'dev'
Requires-Dist: pip-tools ; extra == 'dev'
Requires-Dist: pyflyby ; extra == 'dev'
Requires-Dist: python-semantic-release ; extra == 'dev'
Requires-Dist: twine ; extra == 'dev'
Requires-Dist: vendorize ; extra == 'dev'
Provides-Extra: docs
Requires-Dist: docutils ; extra == 'docs'
Requires-Dist: sphinx ; extra == 'docs'
Requires-Dist: sphinx-click ; extra == 'docs'
Requires-Dist: sphinx-rtd-theme ; extra == 'docs'
Requires-Dist: sphinxcontrib-napoleon ; extra == 'docs'
Provides-Extra: tests
Requires-Dist: coverage[toml] <7,>=6 ; extra == 'tests'
Requires-Dist: darglint <2,>=1.8.1 ; extra == 'tests'
Requires-Dist: pydocstyle <7,>=6.3 ; extra == 'tests'
Requires-Dist: pytest <8,>=7 ; extra == 'tests'
Requires-Dist: pytest-asyncio <1,>=0.21.1 ; extra == 'tests'
Requires-Dist: pytest-cov <5,>=4 ; extra == 'tests'
Requires-Dist: pytest-doctestplus <1,>=0.13 ; extra == 'tests'
Requires-Dist: pytest-mock <4,>=3 ; extra == 'tests'
Requires-Dist: pytest-xdist <3,>=2 ; extra == 'tests'
Requires-Dist: pytest-remotedata <1,>=0.4.0 ; extra == 'tests'
Requires-Dist: pytest-lazy-fixture ~=0.6.3 ; extra == 'tests'
Requires-Dist: pytest-sugar <1,>=0.9.7 ; extra == 'tests'
Requires-Dist: responses ==0.21.0 ; extra == 'tests'
Requires-Dist: requests-mock <2,>=1.10.0 ; extra == 'tests'
Requires-Dist: ruff <0.1,>=0.0.282 ; extra == 'tests'
Requires-Dist: tox <5,>=4.6.4 ; extra == 'tests'
Requires-Dist: types-pytest-lazy-fixture >=0.6.3.3 ; extra == 'tests'
